Metadata-Version: 2.4
Name: airbender-py-client
Version: 0.2.12
Summary: Core Airbender client SDK for Python
Project-URL: Homepage, https://github.com/rangle/airbender
Project-URL: Documentation, https://github.com/rangle/airbender/tree/main/libs/airbender-py/client
Project-URL: Repository, https://github.com/rangle/airbender.git
Project-URL: Issues, https://github.com/rangle/airbender/issues
Author-email: "Rangle.io" <info@rangle.io>
License: Apache-2.0
Keywords: ai,airbender,governance,llm,monitoring
Classifier: Development Status :: 3 - Alpha
Classifier: Intended Audience :: Developers
Classifier: License :: OSI Approved :: Apache Software License
Classifier: Programming Language :: Python :: 3
Classifier: Programming Language :: Python :: 3.12
Classifier: Programming Language :: Python :: 3.13
Requires-Python: >=3.12
Requires-Dist: annotated-types==0.7.0
Requires-Dist: anyio==4.9.0
Requires-Dist: black==25.1.0
Requires-Dist: certifi==2025.6.15
Requires-Dist: click==8.2.1
Requires-Dist: colorama==0.4.6; sys_platform == 'win32'
Requires-Dist: coverage==7.9.1
Requires-Dist: h11==0.16.0
Requires-Dist: httpcore==1.0.9
Requires-Dist: httpx==0.28.1
Requires-Dist: idna==3.10
Requires-Dist: iniconfig==2.1.0
Requires-Dist: mypy-extensions==1.1.0
Requires-Dist: mypy==1.16.1
Requires-Dist: packaging==24.2
Requires-Dist: pathspec==0.12.1
Requires-Dist: platformdirs==4.3.8
Requires-Dist: pluggy==1.6.0
Requires-Dist: pydantic-core==2.33.2
Requires-Dist: pydantic==2.11.7
Requires-Dist: pygments==2.19.1
Requires-Dist: pytest-asyncio==1.0.0
Requires-Dist: pytest-cov==6.2.1
Requires-Dist: pytest-httpx==0.35.0
Requires-Dist: pytest==8.4.0
Requires-Dist: python-dotenv==1.1.0
Requires-Dist: ruff==0.11.13
Requires-Dist: sniffio==1.3.1
Requires-Dist: typing-extensions==4.14.0
Requires-Dist: typing-inspection==0.4.1
Provides-Extra: dev
Requires-Dist: black>=24.0; extra == 'dev'
Requires-Dist: mypy>=1.10; extra == 'dev'
Requires-Dist: pytest-asyncio>=0.23; extra == 'dev'
Requires-Dist: pytest-cov>=5.0; extra == 'dev'
Requires-Dist: pytest-httpx>=0.30; extra == 'dev'
Requires-Dist: pytest>=8.0; extra == 'dev'
Requires-Dist: ruff>=0.4; extra == 'dev'
